{
  "data": {
    "results": [
      {
        "quote": {
          "instrument_id": "92d67a9a-2e1c-4ef9-97d2-01724ca19835",
          "ask_price": "2.200000",
          "ask_size": 8,
          "bid_price": "0.000000",
          "bid_size": 0,
          "break_even_price": "169.990000",
          "adjusted_mark_price": "0.010000",
          "mark_price": "1.100000",
          "high_fill_rate_buy_price": "",
          "low_fill_rate_buy_price": "",
          "high_fill_rate_sell_price": "",
          "low_fill_rate_sell_price": "",
          "previous_close_price": "0.010000",
          "previous_close_date": "2026-07-07",
          "implied_volatility": "0.574812",
          "delta": "-0.000768",
          "gamma": "0.000054",
          "rho": "-0.000183",
          "theta": "-0.002030",
          "vega": "0.002113",
          "open_interest": 0,
          "volume": 0,
          "chance_of_profit_long": "0.001330",
          "chance_of_profit_short": "0.998670",
          "updated_at": "2026-07-08T19:59:59.370146911Z"
        }
      },
      {
        "quote": {
          "instrument_id": "ab3bf62c-0d0a-4125-9bfc-dbde62c89c64",
          "ask_price": "114.100000",
          "ask_size": 1,
          "bid_price": "110.700000",
          "bid_size": 1,
          "break_even_price": "282.400000",
          "adjusted_mark_price": "112.400000",
          "mark_price": "112.400000",
          "high_fill_rate_buy_price": "112.853000",
          "low_fill_rate_buy_price": "111.126000",
          "high_fill_rate_sell_price": "111.946000",
          "low_fill_rate_sell_price": "113.673000",
          "previous_close_price": "112.950000",
          "previous_close_date": "2026-07-07",
          "implied_volatility": "1.019165",
          "delta": "0.970321",
          "gamma": "0.000827",
          "rho": "0.129790",
          "theta": "-0.108976",
          "vega": "0.053924",
          "open_interest": 0,
          "volume": 0,
          "chance_of_profit_long": "0.438909",
          "chance_of_profit_short": "0.561091",
          "updated_at": "2026-07-08T19:59:59.902612603Z"
        }
      },
      {
        "quote": {
          "instrument_id": "2a95297c-94a3-4a7d-af12-f9f3cceff2da",
          "ask_price": "2.250000",
          "ask_size": 1,
          "bid_price": "0.000000",
          "bid_size": 0,
          "break_even_price": "174.990000",
          "adjusted_mark_price": "0.010000",
          "mark_price": "1.125000",
          "high_fill_rate_buy_price": "",
          "low_fill_rate_buy_price": "",
          "high_fill_rate_sell_price": "",
          "low_fill_rate_sell_price": "",
          "previous_close_price": "0.010000",
          "previous_close_date": "2026-07-07",
          "implied_volatility": "0.543818",
          "delta": "-0.000811",
          "gamma": "0.000069",
          "rho": "-0.000193",
          "theta": "-0.002017",
          "vega": "0.002221",
          "open_interest": 0,
          "volume": 0,
          "chance_of_profit_long": "0.001361",
          "chance_of_profit_short": "0.998639",
          "updated_at": "2026-07-08T19:58:40.700297542Z"
        }
      },
      {
        "quote": {
          "instrument_id": "c96f46ce-3b6d-4de4-9d5c-1c27db99d4ba",
          "ask_price": "109.200000",
          "ask_size": 3,
          "bid_price": "105.800000",
          "bid_size": 1,
          "break_even_price": "282.500000",
          "adjusted_mark_price": "107.500000",
          "mark_price": "107.500000",
          "high_fill_rate_buy_price": "107.963000",
          "low_fill_rate_buy_price": "106.236000",
          "high_fill_rate_sell_price": "107.036000",
          "low_fill_rate_sell_price": "108.763000",
          "previous_close_price": "108.000000",
          "previous_close_date": "2026-07-07",
          "implied_volatility": "0.983551",
          "delta": "0.967113",
          "gamma": "0.000944",
          "rho": "0.133031",
          "theta": "-0.114073",
          "vega": "0.058701",
          "open_interest": 0,
          "volume": 0,
          "chance_of_profit_long": "0.440286",
          "chance_of_profit_short": "0.559714",
          "updated_at": "2026-07-08T19:59:59.438192761Z"
        }
      },
      {
        "quote": {
          "instrument_id": "a06f3b30-b7b3-4c49-95a6-d4cb9fe1f884",
          "ask_price": "2.300000",
          "ask_size": 1,
          "bid_price": "0.000000",
          "bid_size": 0,
          "break_even_price": "179.990000",
          "adjusted_mark_price": "0.010000",
          "mark_price": "1.150000",
          "high_fill_rate_buy_price": "",
          "low_fill_rate_buy_price": "",
          "high_fill_rate_sell_price": "",
          "low_fill_rate_sell_price": "",
          "previous_close_price": "0.010000",
          "previous_close_date": "2026-07-07",
          "implied_volatility": "0.513569",
          "delta": "-0.000856",
          "gamma": "0.000075",
          "rho": "-0.000203",
          "theta": "-0.002001",
          "vega": "0.002334",
          "open_interest": 0,
          "volume": 0,
          "chance_of_profit_long": "0.001394",
          "chance_of_profit_short": "0.998606",
          "updated_at": "2026-07-08T19:59:59.910360432Z"
        }
      },
      {
        "quote": {
          "instrument_id": "e835012f-7958-4fb4-8119-9c682f4a26d1",
          "ask_price": "104.100000",
          "ask_size": 1,
          "bid_price": "101.000000",
          "bid_size": 1,
          "break_even_price": "282.550000",
          "adjusted_mark_price": "102.550000",
          "mark_price": "102.550000",
          "high_fill_rate_buy_price": "102.976000",
          "low_fill_rate_buy_price": "101.401000",
          "high_fill_rate_sell_price": "102.123000",
          "low_fill_rate_sell_price": "103.698000",
          "previous_close_price": "103.050000",
          "previous_close_date": "2026-07-07",
          "implied_volatility": "0.939444",
          "delta": "0.964710",
          "gamma": "0.001037",
          "rho": "0.136496",
          "theta": "-0.115691",
          "vega": "0.062205",
          "open_interest": 1,
          "volume": 0,
          "chance_of_profit_long": "0.442313",
          "chance_of_profit_short": "0.557687",
          "updated_at": "2026-07-08T19:59:58.625209338Z"
        }
      },
      {
        "quote": {
          "instrument_id": "04b47a7e-1e46-45fe-9d62-4cf5300f06ca",
          "ask_price": "2.450000",
          "ask_size": 5,
          "bid_price": "0.000000",
          "bid_size": 0,
          "break_even_price": "184.990000",
          "adjusted_mark_price": "0.010000",
          "mark_price": "1.225000",
          "high_fill_rate_buy_price": "",
          "low_fill_rate_buy_price": "",
          "high_fill_rate_sell_price": "",
          "low_fill_rate_sell_price": "",
          "previous_close_price": "0.010000",
          "previous_close_date": "2026-07-07",
          "implied_volatility": "0.484064",
          "delta": "-0.000905",
          "gamma": "0.000073",
          "rho": "-0.000214",
          "theta": "-0.001983",
          "vega": "0.002457",
          "open_interest": 0,
          "volume": 0,
          "chance_of_profit_long": "0.001430",
          "chance_of_profit_short": "0.998570",
          "updated_at": "2026-07-08T19:59:59.908109911Z"
        }
      },
      {
        "quote": {
          "instrument_id": "c74b7588-f4a0-4d81-bd57-d31d95fb17e8",
          "ask_price": "99.400000",
          "ask_size": 2,
          "bid_price": "96.000000",
          "bid_size": 1,
          "break_even_price": "282.700000",
          "adjusted_mark_price": "97.700000",
          "mark_price": "97.700000",
          "high_fill_rate_buy_price": "98.159000",
          "low_fill_rate_buy_price": "96.432000",
          "high_fill_rate_sell_price": "97.240000",
          "low_fill_rate_sell_price": "98.967000",
          "previous_close_price": "98.200000",
          "previous_close_date": "2026-07-07",
          "implied_volatility": "0.910684",
          "delta": "0.960052",
          "gamma": "0.001187",
          "rho": "0.139368",
          "theta": "-0.123224",
          "vega": "0.068833",
          "open_interest": 0,
          "volume": 0,
          "chance_of_profit_long": "0.442980",
          "chance_of_profit_short": "0.557020",
          "updated_at": "2026-07-08T19:59:59.43895927Z"
        }
      },
      {
        "quote": {
          "instrument_id": "09355bfd-10e9-4ecf-917b-c3ae65295047",
          "ask_price": "2.500000",
          "ask_size": 3,
          "bid_price": "0.000000",
          "bid_size": 0,
          "break_even_price": "189.990000",
          "adjusted_mark_price": "0.010000",
          "mark_price": "1.250000",
          "high_fill_rate_buy_price": "",
          "low_fill_rate_buy_price": "",
          "high_fill_rate_sell_price": "",
          "low_fill_rate_sell_price": "",
          "previous_close_price": "0.010000",
          "previous_close_date": "2026-07-07",
          "implied_volatility": "0.455454",
          "delta": "-0.000962",
          "gamma": "0.000089",
          "rho": "-0.000227",
          "theta": "-0.001972",
          "vega": "0.002599",
          "open_interest": 0,
          "volume": 0,
          "chance_of_profit_long": "0.001477",
          "chance_of_profit_short": "0.998523",
          "updated_at": "2026-07-08T19:59:57.914510304Z"
        }
      },
      {
        "quote": {
          "instrument_id": "c146ad2a-e22e-4a3c-9472-7889e9826179",
          "ask_price": "94.500000",
          "ask_size": 7,
          "bid_price": "91.200000",
          "bid_size": 1,
          "break_even_price": "282.850000",
          "adjusted_mark_price": "92.850000",
          "mark_price": "92.850000",
          "high_fill_rate_buy_price": "93.311000",
          "low_fill_rate_buy_price": "91.635000",
          "high_fill_rate_sell_price": "92.388000",
          "low_fill_rate_sell_price": "94.064000",
          "previous_close_price": "93.300000",
          "previous_close_date": "2026-07-07",
          "implied_volatility": "0.880435",
          "delta": "0.955086",
          "gamma": "0.001349",
          "rho": "0.142168",
          "theta": "-0.130235",
          "vega": "0.075676",
          "open_interest": 1,
          "volume": 0,
          "chance_of_profit_long": "0.443657",
          "chance_of_profit_short": "0.556343",
          "updated_at": "2026-07-08T19:59:59.368221027Z"
        }
      },
      {
        "quote": {
          "instrument_id": "7bef246c-7424-45e2-a588-38c03df8091e",
          "ask_price": "89.700000",
          "ask_size": 3,
          "bid_price": "86.300000",
          "bid_size": 1,
          "break_even_price": "283.000000",
          "adjusted_mark_price": "88.000000",
          "mark_price": "88.000000",
          "high_fill_rate_buy_price": "88.463000",
          "low_fill_rate_buy_price": "86.736000",
          "high_fill_rate_sell_price": "87.536000",
          "low_fill_rate_sell_price": "89.263000",
          "previous_close_price": "88.500000",
          "previous_close_date": "2026-07-07",
          "implied_volatility": "0.848845",
          "delta": "0.949787",
          "gamma": "0.001526",
          "rho": "0.144893",
          "theta": "-0.136678",
          "vega": "0.082749",
          "open_interest": 0,
          "volume": 0,
          "chance_of_profit_long": "0.444327",
          "chance_of_profit_short": "0.555673",
          "updated_at": "2026-07-08T19:59:59.440062143Z"
        }
      },
      {
        "quote": {
          "instrument_id": "bc6b6c3e-53df-4420-b551-316a51316fa3",
          "ask_price": "2.650000",
          "ask_size": 2,
          "bid_price": "0.000000",
          "bid_size": 0,
          "break_even_price": "194.990000",
          "adjusted_mark_price": "0.010000",
          "mark_price": "1.325000",
          "high_fill_rate_buy_price": "",
          "low_fill_rate_buy_price": "",
          "high_fill_rate_sell_price": "",
          "low_fill_rate_sell_price": "",
          "previous_close_price": "0.010000",
          "previous_close_date": "2026-07-07",
          "implied_volatility": "0.427291",
          "delta": "-0.001020",
          "gamma": "0.000091",
          "rho": "-0.000240",
          "theta": "-0.001950",
          "vega": "0.002742",
          "open_interest": 2,
          "volume": 0,
          "chance_of_profit_long": "0.001523",
          "chance_of_profit_short": "0.998477",
          "updated_at": "2026-07-08T19:59:59.910871371Z"
        }
      },
      {
        "quote": {
          "instrument_id": "96b40a2c-0b7c-4f9d-b846-8a8bc3898c5a",
          "ask_price": "2.800000",
          "ask_size": 1,
          "bid_price": "0.000000",
          "bid_size": 0,
          "break_even_price": "199.990000",
          "adjusted_mark_price": "0.010000",
          "mark_price": "1.400000",
          "high_fill_rate_buy_price": "",
          "low_fill_rate_buy_price": "",
          "high_fill_rate_sell_price": "",
          "low_fill_rate_sell_price": "",
          "previous_close_price": "0.010000",
          "previous_close_date": "2026-07-07",
          "implied_volatility": "0.399873",
          "delta": "-0.001087",
          "gamma": "0.000106",
          "rho": "-0.000256",
          "theta": "-0.001933",
          "vega": "0.002907",
          "open_interest": 0,
          "volume": 0,
          "chance_of_profit_long": "0.001579",
          "chance_of_profit_short": "0.998421",
          "updated_at": "2026-07-08T19:59:58.516541057Z"
        }
      },
      {
        "quote": {
          "instrument_id": "e4fb5be4-8a67-4543-aa6e-295e5e608d35",
          "ask_price": "84.900000",
          "ask_size": 10,
          "bid_price": "81.500000",
          "bid_size": 5,
          "break_even_price": "283.200000",
          "adjusted_mark_price": "83.200000",
          "mark_price": "83.200000",
          "high_fill_rate_buy_price": "83.797000",
          "low_fill_rate_buy_price": "82.078000",
          "high_fill_rate_sell_price": "82.602000",
          "low_fill_rate_sell_price": "84.321000",
          "previous_close_price": "83.700000",
          "previous_close_date": "2026-07-07",
          "implied_volatility": "0.821576",
          "delta": "0.943082",
          "gamma": "0.001745",
          "rho": "0.147258",
          "theta": "-0.145153",
          "vega": "0.091388",
          "open_interest": 0,
          "volume": 0,
          "chance_of_profit_long": "0.444415",
          "chance_of_profit_short": "0.555585",
          "updated_at": "2026-07-08T19:59:59.682087398Z"
        }
      },
      {
        "quote": {
          "instrument_id": "6e6a9622-24a2-46f2-8877-7445534eb104",
          "ask_price": "80.100000",
          "ask_size": 8,
          "bid_price": "76.700000",
          "bid_size": 5,
          "break_even_price": "283.400000",
          "adjusted_mark_price": "78.400000",
          "mark_price": "78.400000",
          "high_fill_rate_buy_price": "78.995000",
          "low_fill_rate_buy_price": "77.275000",
          "high_fill_rate_sell_price": "77.804000",
          "low_fill_rate_sell_price": "79.524000",
          "previous_close_price": "78.900000",
          "previous_close_date": "2026-07-07",
          "implied_volatility": "0.792518",
          "delta": "0.935908",
          "gamma": "0.001984",
          "rho": "0.149514",
          "theta": "-0.152861",
          "vega": "0.100285",
          "open_interest": 0,
          "volume": 0,
          "chance_of_profit_long": "0.444483",
          "chance_of_profit_short": "0.555517",
          "updated_at": "2026-07-08T19:59:59.097236762Z"
        }
      },
      {
        "quote": {
          "instrument_id": "d84cd1fe-f0ee-4cd6-a469-3a073b38bd84",
          "ask_price": "3.100000",
          "ask_size": 13,
          "bid_price": "0.000000",
          "bid_size": 0,
          "break_even_price": "204.990000",
          "adjusted_mark_price": "0.010000",
          "mark_price": "1.550000",
          "high_fill_rate_buy_price": "",
          "low_fill_rate_buy_price": "",
          "high_fill_rate_sell_price": "",
          "low_fill_rate_sell_price": "",
          "previous_close_price": "0.010000",
          "previous_close_date": "2026-07-07",
          "implied_volatility": "0.373051",
          "delta": "-0.001162",
          "gamma": "0.000132",
          "rho": "-0.000273",
          "theta": "-0.001914",
          "vega": "0.003090",
          "open_interest": 1,
          "volume": 1,
          "chance_of_profit_long": "0.001643",
          "chance_of_profit_short": "0.998357",
          "updated_at": "2026-07-08T19:59:58.239743415Z"
        }
      },
      {
        "quote": {
          "instrument_id": "05c64710-800f-4b3d-88dd-81029f311e43",
          "ask_price": "2.400000",
          "ask_size": 1,
          "bid_price": "0.000000",
          "bid_size": 0,
          "break_even_price": "209.990000",
          "adjusted_mark_price": "0.010000",
          "mark_price": "1.200000",
          "high_fill_rate_buy_price": "",
          "low_fill_rate_buy_price": "",
          "high_fill_rate_sell_price": "",
          "low_fill_rate_sell_price": "",
          "previous_close_price": "0.010000",
          "previous_close_date": "2026-07-07",
          "implied_volatility": "0.346825",
          "delta": "-0.001248",
          "gamma": "0.000131",
          "rho": "-0.000292",
          "theta": "-0.001897",
          "vega": "0.003299",
          "open_interest": 46,
          "volume": 0,
          "chance_of_profit_long": "0.001719",
          "chance_of_profit_short": "0.998281",
          "updated_at": "2026-07-08T13:30:49.735587872Z"
        }
      },
      {
        "quote": {
          "instrument_id": "61b4850b-0227-4679-a933-894ba4327ca0",
          "ask_price": "75.400000",
          "ask_size": 8,
          "bid_price": "72.000000",
          "bid_size": 1,
          "break_even_price": "283.700000",
          "adjusted_mark_price": "73.700000",
          "mark_price": "73.700000",
          "high_fill_rate_buy_price": "74.172000",
          "low_fill_rate_buy_price": "72.445000",
          "high_fill_rate_sell_price": "73.227000",
          "low_fill_rate_sell_price": "74.954000",
          "previous_close_price": "74.200000",
          "previous_close_date": "2026-07-07",
          "implied_volatility": "0.770614",
          "delta": "0.926245",
          "gamma": "0.002282",
          "rho": "0.151126",
          "theta": "-0.164283",
          "vega": "0.111752",
          "open_interest": 0,
          "volume": 0,
          "chance_of_profit_long": "0.443509",
          "chance_of_profit_short": "0.556491",
          "updated_at": "2026-07-08T19:59:59.480538667Z"
        }
      },
      {
        "quote": {
          "instrument_id": "399fe941-0e54-4bdf-9e2c-1b4abbf717df",
          "ask_price": "3.700000",
          "ask_size": 14,
          "bid_price": "0.000000",
          "bid_size": 0,
          "break_even_price": "214.990000",
          "adjusted_mark_price": "0.010000",
          "mark_price": "1.850000",
          "high_fill_rate_buy_price": "",
          "low_fill_rate_buy_price": "",
          "high_fill_rate_sell_price": "",
          "low_fill_rate_sell_price": "",
          "previous_close_price": "1.930000",
          "previous_close_date": "2026-07-07",
          "implied_volatility": "0.321046",
          "delta": "-0.001343",
          "gamma": "0.000176",
          "rho": "-0.000314",
          "theta": "-0.001875",
          "vega": "0.003527",
          "open_interest": 2,
          "volume": 0,
          "chance_of_profit_long": "0.001803",
          "chance_of_profit_short": "0.998197",
          "updated_at": "2026-07-08T19:59:59.367905765Z"
        }
      },
      {
        "quote": {
          "instrument_id": "82c460d0-ffdf-488c-911e-3932fd72672a",
          "ask_price": "70.800000",
          "ask_size": 5,
          "bid_price": "67.400000",
          "bid_size": 1,
          "break_even_price": "284.100000",
          "adjusted_mark_price": "69.100000",
          "mark_price": "69.100000",
          "high_fill_rate_buy_price": "69.568000",
          "low_fill_rate_buy_price": "67.841000",
          "high_fill_rate_sell_price": "68.631000",
          "low_fill_rate_sell_price": "70.358000",
          "previous_close_price": "69.550000",
          "previous_close_date": "2026-07-07",
          "implied_volatility": "0.753924",
          "delta": "0.914033",
          "gamma": "0.002605",
          "rho": "0.152074",
          "theta": "-0.178746",
          "vega": "0.125485",
          "open_interest": 0,
          "volume": 0,
          "chance_of_profit_long": "0.441572",
          "chance_of_profit_short": "0.558428",
          "updated_at": "2026-07-08T19:59:59.680209241Z"
        }
      },
      {
        "quote": {
          "instrument_id": "3ab2dcc4-19b7-4ccc-b23f-574eaf40cb64",
          "ask_price": "3.000000",
          "ask_size": 11,
          "bid_price": "0.050000",
          "bid_size": 13,
          "break_even_price": "218.470000",
          "adjusted_mark_price": "1.530000",
          "mark_price": "1.525000",
          "high_fill_rate_buy_price": "2.061000",
          "low_fill_rate_buy_price": "0.572000",
          "high_fill_rate_sell_price": "0.988000",
          "low_fill_rate_sell_price": "2.477000",
          "previous_close_price": "1.800000",
          "previous_close_date": "2026-07-07",
          "implied_volatility": "0.613108",
          "delta": "-0.066392",
          "gamma": "0.002612",
          "rho": "-0.016266",
          "theta": "-0.104775",
          "vega": "0.103068",
          "open_interest": 2,
          "volume": 1,
          "chance_of_profit_long": "0.085533",
          "chance_of_profit_short": "0.914467",
          "updated_at": "2026-07-08T19:59:59.365950598Z"
        }
      },
      {
        "quote": {
          "instrument_id": "b77c0bfd-56e0-4ec9-b696-16ec158b2919",
          "ask_price": "66.200000",
          "ask_size": 5,
          "bid_price": "62.900000",
          "bid_size": 1,
          "break_even_price": "284.550000",
          "adjusted_mark_price": "64.550000",
          "mark_price": "64.550000",
          "high_fill_rate_buy_price": "65.008000",
          "low_fill_rate_buy_price": "63.332000",
          "high_fill_rate_sell_price": "64.091000",
          "low_fill_rate_sell_price": "65.767000",
          "previous_close_price": "64.950000",
          "previous_close_date": "2026-07-07",
          "implied_volatility": "0.736788",
          "delta": "0.900299",
          "gamma": "0.002983",
          "rho": "0.152635",
          "theta": "-0.193285",
          "vega": "0.140024",
          "open_interest": 0,
          "volume": 2,
          "chance_of_profit_long": "0.439194",
          "chance_of_profit_short": "0.560806",
          "updated_at": "2026-07-08T19:59:59.677406448Z"
        }
      },
      {
        "quote": {
          "instrument_id": "5aefbb43-8fb7-461b-8bbe-70cc7d3424f0",
          "ask_price": "4.500000",
          "ask_size": 11,
          "bid_price": "0.400000",
          "bid_size": 18,
          "break_even_price": "222.550000",
          "adjusted_mark_price": "2.450000",
          "mark_price": "2.450000",
          "high_fill_rate_buy_price": "3.165000",
          "low_fill_rate_buy_price": "1.091000",
          "high_fill_rate_sell_price": "1.734000",
          "low_fill_rate_sell_price": "3.808000",
          "previous_close_price": "2.800000",
          "previous_close_date": "2026-07-07",
          "implied_volatility": "0.644550",
          "delta": "-0.094074",
          "gamma": "0.003263",
          "rho": "-0.023217",
          "theta": "-0.143280",
          "vega": "0.134181",
          "open_interest": 1,
          "volume": 0,
          "chance_of_profit_long": "0.116542",
          "chance_of_profit_short": "0.883458",
          "updated_at": "2026-07-08T19:59:58.164198347Z"
        }
      },
      {
        "quote": {
          "instrument_id": "a5538e3e-a3a9-4577-b9bf-e4157acebfc1",
          "ask_price": "61.500000",
          "ask_size": 3,
          "bid_price": "58.300000",
          "bid_size": 1,
          "break_even_price": "284.900000",
          "adjusted_mark_price": "59.900000",
          "mark_price": "59.900000",
          "high_fill_rate_buy_price": "60.344000",
          "low_fill_rate_buy_price": "58.719000",
          "high_fill_rate_sell_price": "59.455000",
          "low_fill_rate_sell_price": "61.080000",
          "previous_close_price": "60.450000",
          "previous_close_date": "2026-07-07",
          "implied_volatility": "0.709072",
          "delta": "0.887636",
          "gamma": "0.003373",
          "rho": "0.153522",
          "theta": "-0.201981",
          "vega": "0.152662",
          "open_interest": 0,
          "volume": 0,
          "chance_of_profit_long": "0.437608",
          "chance_of_profit_short": "0.562392",
          "updated_at": "2026-07-08T19:59:58.868382911Z"
        }
      },
      {
        "quote": {
          "instrument_id": "5009792e-1925-455e-b95a-33317edd907d",
          "ask_price": "4.900000",
          "ask_size": 11,
          "bid_price": "0.850000",
          "bid_size": 6,
          "break_even_price": "227.120000",
          "adjusted_mark_price": "2.880000",
          "mark_price": "2.875000",
          "high_fill_rate_buy_price": "3.483000",
          "low_fill_rate_buy_price": "1.427000",
          "high_fill_rate_sell_price": "2.266000",
          "low_fill_rate_sell_price": "4.322000",
          "previous_close_price": "2.330000",
          "previous_close_date": "2026-07-07",
          "implied_volatility": "0.626370",
          "delta": "-0.110149",
          "gamma": "0.003758",
          "rho": "-0.027158",
          "theta": "-0.155951",
          "vega": "0.150507",
          "open_interest": 14,
          "volume": 8,
          "chance_of_profit_long": "0.131713",
          "chance_of_profit_short": "0.868287",
          "updated_at": "2026-07-08T19:59:59.170792929Z"
        }
      }
    ],
    "closes_error": "closes omitted: this tool returns the official close for up to 20 contracts per call; quotes are still included for all 25 requested contracts"
  },
  "guide": "Each entry in results pairs the live quote with the official prior-session close for the same option contract. Current price: use quote.mark_price (adjusted_mark_price when comparing against historical cost basis); verify quote.updated_at is recent before calling it 'current' — otherwise phrase as 'as of <updated_at>'. 1D P&L per contract: (quote.mark_price - close.price) × multiplier × position_quantity (multiplier is typically 100; use trade_value_multiplier from get_option_positions for adjusted contracts). Prefer results[].close.price (official settled close) over quote.previous_close_price; when a result is missing close — either closes_error is set tool-wide, or this contract had no close in an otherwise-successful batch — fall back to quote.previous_close_price and tell the user the official close lookup is unavailable. When close.interpolated is true, surface close.date — the price is not from the requested day. Drop bid/ask when zero."
}