{
  "data": {
    "results": [
      {
        "quote": {
          "instrument_id": "put_EQPT_13_0",
          "open_interest": 100,
          "gamma": 0.002,
          "implied_volatility": "0.45",
          "bid_price": "0.50",
          "ask_price": "0.60",
          "mark_price": "0.55",
          "volume": 12,
          "delta": "-0.5",
          "updated_at": "2026-07-10T00:08:07Z"
        }
      },
      {
        "quote": {
          "instrument_id": "call_EQPT_13_0",
          "open_interest": 100,
          "gamma": 0.002,
          "implied_volatility": "0.45",
          "bid_price": "0.50",
          "ask_price": "0.60",
          "mark_price": "0.55",
          "volume": 20,
          "delta": "0.5",
          "updated_at": "2026-07-10T00:08:07Z"
        }
      },
      {
        "quote": {
          "instrument_id": "put_EQPT_14_0",
          "open_interest": 100,
          "gamma": 0.002,
          "implied_volatility": "0.45",
          "bid_price": "0.50",
          "ask_price": "0.60",
          "mark_price": "0.55",
          "volume": 12,
          "delta": "-0.5",
          "updated_at": "2026-07-10T00:08:07Z"
        }
      },
      {
        "quote": {
          "instrument_id": "call_EQPT_14_0",
          "open_interest": 100,
          "gamma": 0.002,
          "implied_volatility": "0.45",
          "bid_price": "0.50",
          "ask_price": "0.60",
          "mark_price": "0.55",
          "volume": 20,
          "delta": "0.5",
          "updated_at": "2026-07-10T00:08:07Z"
        }
      },
      {
        "quote": {
          "instrument_id": "put_EQPT_15_0",
          "open_interest": 1000,
          "gamma": 0.002,
          "implied_volatility": "0.45",
          "bid_price": "0.50",
          "ask_price": "0.60",
          "mark_price": "0.55",
          "volume": 12,
          "delta": "-0.5",
          "updated_at": "2026-07-10T00:08:07Z"
        }
      },
      {
        "quote": {
          "instrument_id": "call_EQPT_15_0",
          "open_interest": 100,
          "gamma": 0.002,
          "implied_volatility": "0.45",
          "bid_price": "0.50",
          "ask_price": "0.60",
          "mark_price": "0.55",
          "volume": 20,
          "delta": "0.5",
          "updated_at": "2026-07-10T00:08:07Z"
        }
      },
      {
        "quote": {
          "instrument_id": "put_EQPT_16_0",
          "open_interest": 800,
          "gamma": 0.002,
          "implied_volatility": "0.45",
          "bid_price": "0.50",
          "ask_price": "0.60",
          "mark_price": "0.55",
          "volume": 12,
          "delta": "-0.5",
          "updated_at": "2026-07-10T00:08:07Z"
        }
      },
      {
        "quote": {
          "instrument_id": "call_EQPT_16_0",
          "open_interest": 100,
          "gamma": 0.002,
          "implied_volatility": "0.45",
          "bid_price": "0.50",
          "ask_price": "0.60",
          "mark_price": "0.55",
          "volume": 20,
          "delta": "0.5",
          "updated_at": "2026-07-10T00:08:07Z"
        }
      },
      {
        "quote": {
          "instrument_id": "put_EQPT_17_0",
          "open_interest": 1200,
          "gamma": 0.015,
          "implied_volatility": "0.45",
          "bid_price": "0.50",
          "ask_price": "0.60",
          "mark_price": "0.55",
          "volume": 12,
          "delta": "-0.5",
          "updated_at": "2026-07-10T00:08:07Z"
        }
      },
      {
        "quote": {
          "instrument_id": "call_EQPT_17_0",
          "open_interest": 100,
          "gamma": 0.015,
          "implied_volatility": "0.45",
          "bid_price": "0.50",
          "ask_price": "0.60",
          "mark_price": "0.55",
          "volume": 20,
          "delta": "0.5",
          "updated_at": "2026-07-10T00:08:07Z"
        }
      },
      {
        "quote": {
          "instrument_id": "put_EQPT_18_0",
          "open_interest": 100,
          "gamma": 0.015,
          "implied_volatility": "0.45",
          "bid_price": "0.50",
          "ask_price": "0.60",
          "mark_price": "0.55",
          "volume": 12,
          "delta": "-0.5",
          "updated_at": "2026-07-10T00:08:07Z"
        }
      },
      {
        "quote": {
          "instrument_id": "call_EQPT_18_0",
          "open_interest": 500,
          "gamma": 0.015,
          "implied_volatility": "0.45",
          "bid_price": "0.50",
          "ask_price": "0.60",
          "mark_price": "0.55",
          "volume": 20,
          "delta": "0.5",
          "updated_at": "2026-07-10T00:08:07Z"
        }
      },
      {
        "quote": {
          "instrument_id": "put_EQPT_19_0",
          "open_interest": 100,
          "gamma": 0.015,
          "implied_volatility": "0.45",
          "bid_price": "0.50",
          "ask_price": "0.60",
          "mark_price": "0.55",
          "volume": 12,
          "delta": "-0.5",
          "updated_at": "2026-07-10T00:08:07Z"
        }
      },
      {
        "quote": {
          "instrument_id": "call_EQPT_19_0",
          "open_interest": 100,
          "gamma": 0.015,
          "implied_volatility": "0.45",
          "bid_price": "0.50",
          "ask_price": "0.60",
          "mark_price": "0.55",
          "volume": 20,
          "delta": "0.5",
          "updated_at": "2026-07-10T00:08:07Z"
        }
      },
      {
        "quote": {
          "instrument_id": "put_EQPT_20_0",
          "open_interest": 100,
          "gamma": 0.015,
          "implied_volatility": "0.45",
          "bid_price": "0.50",
          "ask_price": "0.60",
          "mark_price": "0.55",
          "volume": 12,
          "delta": "-0.5",
          "updated_at": "2026-07-10T00:08:07Z"
        }
      },
      {
        "quote": {
          "instrument_id": "call_EQPT_20_0",
          "open_interest": 2000,
          "gamma": 0.015,
          "implied_volatility": "0.45",
          "bid_price": "0.50",
          "ask_price": "0.60",
          "mark_price": "0.55",
          "volume": 20,
          "delta": "0.5",
          "updated_at": "2026-07-10T00:08:07Z"
        }
      },
      {
        "quote": {
          "instrument_id": "put_EQPT_21_0",
          "open_interest": 100,
          "gamma": 0.002,
          "implied_volatility": "0.45",
          "bid_price": "0.50",
          "ask_price": "0.60",
          "mark_price": "0.55",
          "volume": 12,
          "delta": "-0.5",
          "updated_at": "2026-07-10T00:08:07Z"
        }
      },
      {
        "quote": {
          "instrument_id": "call_EQPT_21_0",
          "open_interest": 100,
          "gamma": 0.002,
          "implied_volatility": "0.45",
          "bid_price": "0.50",
          "ask_price": "0.60",
          "mark_price": "0.55",
          "volume": 20,
          "delta": "0.5",
          "updated_at": "2026-07-10T00:08:07Z"
        }
      },
      {
        "quote": {
          "instrument_id": "put_EQPT_22_0",
          "open_interest": 100,
          "gamma": 0.002,
          "implied_volatility": "0.45",
          "bid_price": "0.50",
          "ask_price": "0.60",
          "mark_price": "0.55",
          "volume": 12,
          "delta": "-0.5",
          "updated_at": "2026-07-10T00:08:07Z"
        }
      },
      {
        "quote": {
          "instrument_id": "call_EQPT_22_0",
          "open_interest": 100,
          "gamma": 0.002,
          "implied_volatility": "0.45",
          "bid_price": "0.50",
          "ask_price": "0.60",
          "mark_price": "0.55",
          "volume": 20,
          "delta": "0.5",
          "updated_at": "2026-07-10T00:08:07Z"
        }
      },
      {
        "quote": {
          "instrument_id": "put_EQPT_23_0",
          "open_interest": 100,
          "gamma": 0.002,
          "implied_volatility": "0.45",
          "bid_price": "0.50",
          "ask_price": "0.60",
          "mark_price": "0.55",
          "volume": 12,
          "delta": "-0.5",
          "updated_at": "2026-07-10T00:08:07Z"
        }
      },
      {
        "quote": {
          "instrument_id": "call_EQPT_23_0",
          "open_interest": 100,
          "gamma": 0.002,
          "implied_volatility": "0.45",
          "bid_price": "0.50",
          "ask_price": "0.60",
          "mark_price": "0.55",
          "volume": 20,
          "delta": "0.5",
          "updated_at": "2026-07-10T00:08:07Z"
        }
      }
    ]
  }
}